oeaudio/__init__.py
oeaudio/__main__.py
oeaudio/core.py
oeaudio/script.py
open_ephys_audio-0.1.7.dist-info/METADATA
open_ephys_audio-0.1.7.dist-info/WHEEL
open_ephys_audio-0.1.7.dist-info/entry_points.txt
open_ephys_audio-0.1.7.dist-info/top_level.txt
open_ephys_audio-0.1.7.dist-info/RECORD
